firthmodels/__init__.py
firthmodels/_lrt.py
firthmodels/_profile_ci.py
firthmodels/_solvers.py
firthmodels/_utils.py
firthmodels/cox.py
firthmodels/logistic.py
firthmodels/py.typed
firthmodels/separation.py
firthmodels/_numba/__init__.py
firthmodels/_numba/blas_abi.py
firthmodels/_numba/cox.py
firthmodels/_numba/linalg.py
firthmodels/_numba/logistic.py
firthmodels/adapters/__init__.py
firthmodels/adapters/statsmodels.py
firthmodels-0.6.0.dist-info/METADATA
firthmodels-0.6.0.dist-info/WHEEL
firthmodels-0.6.0.dist-info/licenses/LICENSE
firthmodels-0.6.0.dist-info/RECORD
