Metadata-Version: 2.4
Name: firthmodels
Version: 0.6.0
Summary: Firth-penalized models in Python
Project-URL: Homepage, https://github.com/jzluo/firthmodels
Project-URL: Repository, https://github.com/jzluo/firthmodels
Project-URL: Issues, https://github.com/jzluo/firthmodels/issues
Author-email: Jon Luo <20971593+jzluo@users.noreply.github.com>
License-Expression: MIT
License-File: LICENSE
Keywords: bias reduction,cox,cox proportional hazards,firth,firth logistic regression,logistic regression,penalized likelihood,rare events,separation,survival analysis
Classifier: Development Status :: 4 - Beta
Classifier: Intended Audience :: Developers
Classifier: Intended Audience :: Science/Research
Classifier: License :: OSI Approved :: MIT License
Classifier: Operating System :: OS Independent
Classifier: Programming Language :: Python :: 3
Classifier: Programming Language :: Python :: 3.11
Classifier: Programming Language :: Python :: 3.12
Classifier: Programming Language :: Python :: 3.13
Classifier: Programming Language :: Python :: 3.14
Classifier: Topic :: Scientific/Engineering
Requires-Python: >=3.11
Requires-Dist: numpy>=1.24
Requires-Dist: scikit-learn>=1.6
Requires-Dist: scipy>=1.12
Provides-Extra: formula
Requires-Dist: formulaic>=1.2.1; extra == 'formula'
Provides-Extra: numba
Requires-Dist: numba>=0.63; extra == 'numba'
